setup.py
elb_dance/__init__.py
elb_dance/cli.py
elb_dance/docopt.py
elb_dance/main.py
elb_dance/version.py
elb_dance.egg-info/PKG-INFO
elb_dance.egg-info/SOURCES.txt
elb_dance.egg-info/dependency_links.txt
elb_dance.egg-info/entry_points.txt
elb_dance.egg-info/not-zip-safe
elb_dance.egg-info/requires.txt
elb_dance.egg-info/top_level.txt