Metadata-Version: 1.1
Name: elb-dance
Version: 0.2
Summary: elb-dance is used to deregister and register instances with ELB
Home-page: http://github.com/opbeat/elb-dance
Author: Ron Cohen
Author-email: ron@opbeat.com
License: UNKNOWN
Platform: UNKNOWN
Classifier: Intended Audience :: Developers
Classifier: Intended Audience :: System Administrators
Classifier: Operating System :: OS Independent
Classifier: Topic :: Software Development
